pathadder/__init__.py
pathadder/_version.py
pathadder/pathadder.ipynb
pathadder/pathadder.py
pathadder-0.8.dist-info/licenses/LICENSE
pathadder-0.8.dist-info/METADATA
pathadder-0.8.dist-info/WHEEL
pathadder-0.8.dist-info/top_level.txt
pathadder-0.8.dist-info/RECORD
