Metadata-Version: 2.4
Name: pathadder
Version: 0.8
Summary: A Python library for managing and modifying system paths efficiently. (Wattleflow)
Home-page: https://github.com/wattleflow/pathadder.git
Author: WattleFlow
Author-email: wattleflow <wattleflow@outlook.com>
License-Expression: Apache-2.0
Project-URL: homepage, https://github.com/wattleflow/pathadder.git
Project-URL: repository, https://github.com/wattleflow/pathadder.git
Project-URL: documentation, https://github.com/wattleflow/pathadder.git
Keywords: pathadder,python,library,wattleflow
Classifier: Development Status :: 5 - Production/Stable
Classifier: Programming Language :: Python :: 3.7
Classifier: Programming Language :: Python :: 3.8
Classifier: Programming Language :: Python :: 3.9
Classifier: Programming Language :: Python :: 3.10
Classifier: Programming Language :: Python :: 3.11
Classifier: Programming Language :: Python :: 3.12
Classifier: Programming Language :: Python :: 3.13
Classifier: Operating System :: OS Independent
Classifier: Intended Audience :: Developers
Classifier: Topic :: Software Development :: Libraries
Classifier: Topic :: Software Development :: Libraries :: Python Modules
Requires-Python: >=3.7.1
License-File: LICENSE
Dynamic: author
Dynamic: home-page
Dynamic: license-file
Dynamic: requires-python
